fasttopi/__init__.py
fasttopi/api.py
fasttopi/client.py
fasttopi/config.py
fasttopi/config.yaml
fasttopi/dataset.py
fasttopi/experiment.py
fasttopi/model.py
fasttopi/models/baseline.pkl
fasttopi/models/model.pkl
fasttopi/models/models-training.pkl
fasttopi-0.30.dist-info/METADATA
fasttopi-0.30.dist-info/WHEEL
fasttopi-0.30.dist-info/top_level.txt
fasttopi-0.30.dist-info/RECORD
