Metadata-Version: 2.1
Name: fasttopi
Version: 0.30
Summary: news categories classifiers for news title
Home-page: UNKNOWN
Author: Yamen Ajjour
Author-email: yajjour@hotmail.com
License: UNKNOWN
Platform: UNKNOWN
Requires-Dist: scikit-learn (==1.0.1)
Requires-Dist: pandas
Requires-Dist: fastapi
Requires-Dist: uvicorn
Requires-Dist: pyyaml
